plate_package/__init__.py
plate_package/py.typed
plate_package-0.0.2.dist-info/METADATA
plate_package-0.0.2.dist-info/WHEEL
plate_package-0.0.2.dist-info/RECORD
