Metadata-Version: 2.1
Name: plate_package
Version: 0.0.2
Summary: 
Home-page: https://github.com/lukin0110/poetry-copier-package-test/
License: Proprietary
Requires-Python: >=3.11.6,<4.0
Classifier: License :: Other/Proprietary License
Classifier: Programming Language :: Python :: 3
Classifier: Programming Language :: Python :: 3.12
Requires-Dist: poethepoet (>=0.24.4)
Requires-Dist: pydantic (>=2.5.3)
Project-URL: Repository, https://github.com/lukin0110/poetry-copier-package-test/
